[
  {
    "id": "11",
    "title": "Family and Relationships",
    "active": false
  },
  {
    "id": "12",
    "title": "Children and Young People",
    "active": false
  },
  {
    "id": "13",
    "title": "Crime and offences",
    "active": false
  },
  {
    "id": "14",
    "title": "Neighbours",
    "active": false
  },
  {
    "id": "15",
    "title": "Courts and Tribunals",
    "active": false
  },
  {
    "id": "16",
    "title": "Motor Vehicles and Traffic Offences",
    "active": false
  },
  {
    "id": "131",
    "title": "Apprehended Violence Orders (AVOs)",
    "active": false,
    "parent": "13"
  },
  {
    "id": "132",
    "title": "Arrest",
    "active": false,
    "parent": "13"
  },
  {
    "id": "133",
    "title": "Child Abuse",
    "active": false,
    "parent": "13"
  },
  {
    "id": "134",
    "title": "Drink Driving",
    "active": false,
    "parent": "13",
    "image": "drink-driving",
    "desc": "Legal Aid NSW <b>does</b> provide support  for this legal matter. You will soon be provided with a guide which will help you prepare for the next steps in your legal situation.",
    "note": "<p><strong>Please note</strong></p><p>If you answer &lsquo;YES&rsquo; to either of these questions, you should seek legal help as soon as possible:&nbsp;</p><ol> <li>Is this a mid to high range drink driving offence?</li><li>Have you been convicted of any drink driving offences in the last five years?</li></ol>",
    "aboutYouSteps": 2,
    "aboutYouCurrent": 1,
    "aboutYouStep2Title": "Do any of these apply to you?",
    "imageAboutYou": "about-you",
    "imageYourGuide": "your-guide",
    "problemQuestions": [
      {
        "id": 1,
        "desc": "Where you in the high, medium or low range?",
        "multipleSelect": false,
        "options": [
          {
            "id": 1,
            "desc": "Low",
            "checked": false,
            "name": "ay-chk-1"
          },
          {
            "id": 2,
            "desc": "Medium",
            "checked": false,
            "name": "ay-chk-2"
          },
          {
            "id": 3,
            "desc": "High",
            "checked": false,
            "name": "ay-chk-3"
          },
          {
            "id": 4,
            "desc": "I'm not sure",
            "checked": false,
            "name": "ay-chk-4"
          }
        ]
      },
      {
        "id": 2,
        "desc": "Do you need to be in court in the next three days?",
        "multipleSelect": false,
        "options": [
          {
            "id": 1,
            "desc": "Yes",
            "checked": false,
            "name": "ay-chk-1"
          },
          {
            "id": 2,
            "desc": "No",
            "checked": false,
            "name": "ay-chk-2"
          }
        ]
      }
    ]
  },
  {
    "id": "135",
    "title": "Drugs",
    "active": false,
    "parent": "13"
  },
  {
    "id": "136",
    "title": "Juvenile Justice",
    "active": false,
    "parent": "13"
  }
]
